<?xml version="1.0" encoding="UTF-8"?>
<configuration>

    <!-- 콘솔에 로그 출력 -->
    <appender name="CONSOLE" class="ch.qos.logback.core.ConsoleAppender">
        <encoder>
            <pattern>%d{HH:mm:ss.SSS} [%thread] %-5level %logger{36} - %msg%n</pattern>
        </encoder>
    </appender>

    <!-- 파일에 로그 저장 (하루 단위 롤링) -->
    <appender name="FILE" class="ch.qos.logback.core.rolling.RollingFileAppender">
        <file>logs/app.log</file> <!-- 현재 로그가 저장될 파일 -->
        <rollingPolicy class="ch.qos.logback.core.rolling.TimeBasedRollingPolicy">
            <!-- 날짜별 로그 파일 이름 -->
            <fileNamePattern>logs/app-%d{yyyy-MM-dd}.log</fileNamePattern>
            <maxHistory>30</maxHistory> <!-- 30일 보관 -->
        </rollingPolicy>
        <encoder>
            <pattern>%d{yyyy-MM-dd HH:mm:ss} [%thread] %-5level %logger{36} - %msg%n</pattern>
        </encoder>
    </appender>

    <!-- 패키지별 로그 레벨 설정 -->
    <logger name="com.example.demo" level="DEBUG"/>

    <!-- 기본 루트 로그 설정: INFO 이상 로그는 콘솔과 파일로 출력 -->
    <root level="INFO">
        <appender-ref ref="CONSOLE"/>
        <appender-ref ref="FILE"/>
    </root>
</configuration>
